fastapi_odm_helper/__init__.py
fastapi_odm_helper/decorators/entity.py
fastapi_odm_helper/dependencies/pagination.py
fastapi_odm_helper/repositories/base.py
fastapi_odm_helper/responses/pagination.py
fastapi_odm_helper-0.0.20.dist-info/METADATA
fastapi_odm_helper-0.0.20.dist-info/WHEEL
fastapi_odm_helper-0.0.20.dist-info/licenses/LICENSE
fastapi_odm_helper-0.0.20.dist-info/RECORD
